{ "height":20,
 "layers":[
        {
         "data":[0, 0, 0, 0, 24, 24, 24, 24, 24, 24, 5, 6, 6, 6, 6, 6, 46, 7, 24, 24, 0, 0, 0, 0, 24, 24, 5, 6, 6, 6, 47, 22, 22, 22, 22, 30, 30, 27, 24, 24, 0, 0, 0, 0, 24, 24, 27, 26, 26, 26, 22, 22, 22, 5, 6, 6, 46, 47, 24, 24, 0, 0, 0, 0, 24, 24, 27, 26, 26, 26, 22, 22, 22, 25, 28, 28, 28, 28, 24, 24, 0, 0, 0, 0, 24, 24, 27, 26, 26, 26, 22, 22, 22, 25, 28, 28, 28, 28, 24, 24, 0, 0, 0, 0, 24, 24, 45, 46, 46, 46, 7, 22, 22, 45, 6, 6, 6, 7, 24, 24, 0, 0, 0, 0, 24, 24, 68, 69, 70, 71, 25, 22, 22, 22, 26, 26, 26, 27, 24, 24, 0, 0, 0, 0, 24, 24, 88, 89, 90, 91, 25, 22, 22, 22, 26, 26, 26, 27, 24, 24, 0, 0, 0, 0, 24, 24, 108, 109, 110, 111, 25, 22, 22, 22, 26, 26, 26, 27, 24, 24, 0, 0, 0, 0, 24, 24, 128, 129, 130, 131, 25, 22, 22, 22, 26, 26, 26, 27, 24, 24, 0, 0, 0, 0, 6, 6, 6, 6, 6, 6, 47, 22, 22, 5, 46, 46, 46, 47, 24, 24, 0, 0, 0, 0, 24, 121, 30, 30, 30, 30, 22, 22, 22, 27, 72, 73, 74, 75, 24, 24, 0, 0, 0, 0, 46, 46, 46, 46, 46, 46, 46, 46, 46, 47, 92, 93, 94, 95, 24, 24, 0, 0, 0, 0, 44, 44, 148, 149, 150, 151, 44, 44, 44, 44, 24, 24, 24, 24, 24, 24, 0, 0, 0, 0, 24, 24, 168, 169, 170, 171, 24, 24, 24, 24, 24, 24, 24, 24, 24, 24, 0, 0, 0, 0, 24, 24, 188, 189, 190, 191, 24, 24, 24, 24, 24, 24, 24, 24, 24, 24, 0, 0, 0, 0, 24, 24, 24, 24, 24, 24, 24, 24, 24, 24, 24, 24, 24, 24, 24, 24, 0, 0, 0, 0, 24, 24, 24, 24, 24, 24, 24, 24, 24, 24, 24, 24, 24, 24, 24, 24, 0, 0, 0, 0, 0, 0, 0, 0, 0, 0, 0, 0, 0, 0, 0, 0, 0, 0, 0, 0, 0, 0, 0, 0, 0, 0, 0, 0, 0, 0, 0, 0, 0, 0, 0, 0, 0, 0, 0, 0],
         "height":20,
         "name":"background",
         "opacity":1,
         "type":"tilelayer",
         "visible":true,
         "width":20,
         "x":0,
         "y":0
        }, 
        {
         "data":[0, 0, 0, 0, 0, 0, 0, 0, 0, 0, 0, 0, 0, 0, 0, 0, 0, 0, 0, 0, 0, 0, 0, 0, 0, 0, 0, 0, 0, 0, 0, 107, 106, 0, 0, 0, 0, 0, 0, 0, 0, 0, 0, 0, 0, 0, 0, 107, 107, 107, 107, 86, 106, 0, 0, 0, 0, 0, 0, 0, 0, 0, 0, 0, 0, 0, 0, 86, 0, 0, 0, 0, 106, 0, 0, 0, 0, 0, 0, 0, 0, 0, 0, 0, 0, 0, 0, 86, 105, 105, 105, 105, 106, 0, 0, 0, 0, 0, 0, 0, 0, 0, 0, 0, 0, 0, 0, 0, 0, 0, 0, 86, 106, 0, 0, 0, 0, 0, 0, 0, 0, 0, 0, 0, 0, 0, 0, 0, 0, 0, 0, 86, 107, 107, 107, 107, 106, 0, 0, 0, 0, 0, 0, 0, 0, 0, 0, 0, 0, 0, 0, 86, 0, 0, 0, 0, 106, 0, 0, 0, 0, 0, 0, 0, 0, 0, 0, 0, 0, 0, 0, 86, 0, 0, 0, 0, 106, 0, 0, 0, 0, 0, 0, 0, 0, 0, 0, 0, 0, 0, 0, 86, 106, 105, 105, 105, 105, 0, 0, 0, 0, 0, 0, 0, 0, 0, 0, 0, 0, 0, 0, 86, 105, 0, 0, 0, 0, 0, 0, 0, 0, 0, 0, 0, 0, 0, 0, 0, 0, 0, 0, 0, 0, 0, 0, 0, 0, 0, 0, 0, 0, 0, 0, 0, 0, 0, 0, 0, 0, 0, 0, 0, 0, 0, 0, 0, 0, 0, 0, 0, 0, 0, 0, 0, 0, 0, 0, 0, 0, 0, 0, 0, 0, 0, 0, 0, 0, 0, 0, 0, 0, 0, 0, 0, 0, 0, 0, 0, 0, 0, 0, 0, 0, 0, 0, 0, 0, 0, 0, 0, 0, 0, 0, 0, 0, 0, 0, 0, 0, 0, 0, 0, 0, 0, 0, 0, 0, 0, 0, 0, 0, 0, 0, 0, 0, 0, 0, 0, 0, 0, 0, 0, 0, 0, 0, 0, 0, 0, 0, 0, 0, 0, 0, 0, 0, 0, 0, 0, 0, 0, 0, 0, 0, 0, 0, 0, 0, 0, 0, 0, 0, 0, 0, 0, 0, 0, 0, 0, 0, 0, 0, 0, 0, 0, 0, 0, 0, 0, 0, 0, 0, 0, 0, 0, 0, 0, 0, 0, 0, 0, 0, 0, 0, 0, 0, 0, 0, 0, 0, 0],
         "height":20,
         "name":"ai",
         "opacity":0.550000011920929,
         "type":"tilelayer",
         "visible":false,
         "width":20,
         "x":0,
         "y":0
        }, 
        {
         "height":20,
         "name":"entities",
         "objects":[
                {
                 "gid":81,
                 "height":32,
                 "name":"Treasure",
                 "properties":
                    {
                     "open":"false",
                     "opengid":"0"
                    },
                 "type":"treasure",
                 "visible":true,
                 "width":32,
                 "x":511,
                 "y":63
                }, 
                {
                 "gid":241,
                 "height":32,
                 "name":"The Thief",
                 "properties":
                    {
                     "speed":"10"
                    },
                 "type":"player",
                 "visible":true,
                 "width":32,
                 "x":198,
                 "y":385
                }, 
                {
                 "gid":261,
                 "height":32,
                 "name":"Black Dude",
                 "properties":
                    {
                     "aifollowdistance":"3",
                     "speed":"6"
                    },
                 "type":"guard",
                 "visible":true,
                 "width":32,
                 "x":386,
                 "y":214
                }],
         "opacity":1,
         "type":"objectgroup",
         "visible":true,
         "width":20,
         "x":0,
         "y":0
        }],
 "orientation":"orthogonal",
 "properties":
    {
     "entities":"..\/entities.json",
     "nextmap":"second.json"
    },
 "tileheight":32,
 "tilesets":[
        {
         "firstgid":1,
         "image":"gfx\/inside.png",
         "imageheight":400,
         "imagewidth":640,
         "margin":0,
         "name":"inside",
         "properties":
            {

            },
         "spacing":0,
         "tileheight":32,
         "tileproperties":
            {
             "104":
                {
                 "aiorder":"left"
                },
             "105":
                {
                 "aiorder":"down"
                },
             "106":
                {
                 "aiorder":"right"
                },
             "120":
                {
                 "isexit":"true",
                 "walkable":"true"
                },
             "121":
                {
                 "isexit":"true",
                 "walkable":"true"
                },
             "140":
                {
                 "isexit":"true",
                 "walkable":"true"
                },
             "141":
                {
                 "isexit":"true",
                 "walkable":"true"
                },
             "21":
                {
                 "walkable":"true"
                },
             "25":
                {
                 "walkable":"true"
                },
             "29":
                {
                 "walkable":"true"
                },
             "64":
                {
                 "aiorder":"stop"
                },
             "65":
                {
                 "aiorder":"follow",
                 "target":"player"
                },
             "66":
                {
                 "aiorder":"rand"
                },
             "84":
                {
                 "aiorder":"pause"
                },
             "85":
                {
                 "aiorder":"up"
                }
            },
         "tilewidth":32
        }, 
        {
         "firstgid":241,
         "image":"gfx\/thief.png",
         "imageheight":480,
         "imagewidth":640,
         "margin":0,
         "name":"thief",
         "properties":
            {

            },
         "spacing":0,
         "tileheight":32,
         "tilewidth":32
        }],
 "tilewidth":32,
 "version":1,
 "width":20
}